pdf_text_extractor/__init__.py
pdf_text_extractor/_version.py
pdf_text_extractor/extractor.py
pdf_text_extractor-0.2.4.dist-info/METADATA
pdf_text_extractor-0.2.4.dist-info/WHEEL
pdf_text_extractor-0.2.4.dist-info/top_level.txt
pdf_text_extractor-0.2.4.dist-info/RECORD
