Metadata-Version: 2.1
Name: pdf-text-extractor
Version: 0.2.4
Summary: Extract text and images from PDF files
Home-page: https://github.com/baxromov/pdf_to_text
Author: Shahzod
Author-email: baxromov.shahzodbek@gmail.com
Project-URL: Documentation, https://pdf-to-text.readthedocs.io/en/latest/
Project-URL: Source Code, https://github.com/baxromov/pdf_to_text
Project-URL: Issue Tracker, https://github.com/baxromov/pdf_to_text/issues
Classifier: Programming Language :: Python :: 3
Classifier: License :: OSI Approved :: MIT License
Classifier: Operating System :: OS Independent
Requires-Python: >=3.12
Requires-Dist: opencv-python
Requires-Dist: pillow
Requires-Dist: PyMuPDF
Requires-Dist: pytesseract
Requires-Dist: ollama
